LICENSE
MANIFEST.in
README.rst
setup.py
django_postgrespool/base.py
django_postgrespool.egg-info/PKG-INFO
django_postgrespool.egg-info/SOURCES.txt
django_postgrespool.egg-info/dependency_links.txt
django_postgrespool.egg-info/requires.txt
django_postgrespool.egg-info/top_level.txt