Metadata-Version: 1.1
Name: django-postgrespool
Version: 0.1.1
Summary: Postgres Connection Pooling for Django.
Home-page: https://github.com/kennethreitz/django-postgrespool
Author: Kenneth Reitz
Author-email: me@kennethreitz.com
License: MIT
Platform: UNKNOWN
Classifier: Intended Audience :: Developers
Classifier: Natural Language :: English
Classifier: License :: OSI Approved :: MIT License
Classifier: Programming Language :: Python
Classifier: Programming Language :: Python :: 2.5
Classifier: Programming Language :: Python :: 2.6
Classifier: Programming Language :: Python :: 2.7
